awshelpers/__init__.py
awshelpers/dynamodb/__init__.py
awshelpers/dynamodb/_connect.py
awshelpers/dynamodb/item.py
awshelpers/ec2/__init__.py
awshelpers/ec2/_connect.py
awshelpers/ec2/describe.py
awshelpers/event/__init__.py
awshelpers/event/dump.py
awshelpers/event/message.py
awshelpers/event/type.py
awshelpers/s3/__init__.py
awshelpers/s3/_connect.py
awshelpers/s3/get.py
awshelpers/ssm/__init__.py
awshelpers/ssm/_connect.py
awshelpers/ssm/get.py
awshelpers/ssm/list.py
awshelpers/ssm/send.py
awshelpers/tests/__init__.py
awshelpers/tests/test_dynamodb.py
awshelpers/tests/test_ec2.py
awshelpers/tests/test_event.py
awshelpers/tests/test_s3.py
awshelpers/tests/test_ssm.py
awshelpers-0.0.48.dist-info/DESCRIPTION.rst
awshelpers-0.0.48.dist-info/METADATA
awshelpers-0.0.48.dist-info/RECORD
awshelpers-0.0.48.dist-info/WHEEL
awshelpers-0.0.48.dist-info/metadata.json
awshelpers-0.0.48.dist-info/top_level.txt
