Metadata-Version: 2.0
Name: awshelpers
Version: 0.0.48
Summary: A package containing modules for common AWS SDK tasks.
Home-page: https://pypi.python.org/pypi/awshelpers
Author: Travis Edgar
Author-email: travis.dolan@gmail.com
License: MIT
Keywords: aws ssm s3 python sdk wrapper
Platform: UNKNOWN
Classifier: Development Status :: 3 - Alpha
Classifier: License :: OSI Approved :: MIT License
Classifier: Programming Language :: Python :: 3.6
Classifier: Topic :: Software Development :: Libraries :: Python Modules
Requires-Dist: boto3
